{"type":"FeatureCollection","features":[{"type":"Feature","id":"f4695","properties":{"name":"Altinum-Florentia","type":"Main Road","certainty":"Conjectured","citation":"Jens Christoffersen","bibliography":"BAtlas 20, Löhberg 2010, Róbert and Máté 2011, Visy 2011","itinerary":"Tabula Peutingeriana, Itinerarium Antonini","lowerDate":100},"geometry":{"type":"MultiLineString","coordinates":[[[18.66936,45.95795],[18.67402,45.97221],[18.678,45.98301],[18.67754,45.98787],[18.67906,45.9921],[18.68095,46.00049],[18.68008,46.00383],[18.67364,46.01958],[18.67679,46.02794],[18.68433,46.03185],[18.68863,46.03345],[18.69613,46.03557],[18.70303,46.03853],[18.70758,46.04104],[18.70925,46.04314],[18.71306,46.04867],[18.71771,46.05247],[18.72113,46.05486],[18.7332,46.05969],[18.74284,46.06591],[18.74971,46.06757],[18.75176,46.0686],[18.75235,46.06942],[18.75492,46.07717],[18.75811,46.08098],[18.7587,46.08155],[18.75872,46.08272]]]}},{"type":"Feature","id":"f4696","properties":{"name":"Altinum-Florentia","type":"Main Road","certainty":"Conjectured","citation":"Jens Christoffersen","bibliography":"BAtlas 20, Löhberg 2010, Róbert and Máté 2011, Visy 2011","itinerary":"Tabula Peutingeriana, Itinerarium Antonini","lowerDate":100},"geometry":{"type":"MultiLineString","coordinates":[[[18.75872,46.08272],[18.75906,46.08336],[18.75844,46.08546],[18.75867,46.08708]]]}},{"type":"Feature","id":"f4699","properties":{"name":"Florentia-Szekszard","type":"Main Road","certainty":"Conjectured","description":"Passes through Ad Statuas and Alisca","citation":"Jens Christoffersen","bibliography":"BAtlas 20, Löhberg 2010, Róbert and Máté 2011, Visy 2011","constructionPeriod":"Septimius Severus (193-211 CE)","itinerary":"Tabula Peutingeriana, Itinerarium Antonini","lowerDate":100},"geometry":{"type":"MultiLineString","coordinates":[[[18.75867,46.08708],[18.75872,46.08746],[18.75782,46.09118],[18.75687,46.09256],[18.7567,46.09359],[18.7569,46.09491],[18.75748,46.09557],[18.75986,46.09758],[18.7602,46.09837],[18.76023,46.10014],[18.75574,46.10882],[18.75072,46.11248],[18.74376,46.12391],[18.74161,46.12546],[18.73703,46.12754],[18.73561,46.1289],[18.73432,46.13158],[18.73185,46.13448],[18.72876,46.13939],[18.7268,46.14276],[18.72473,46.14487],[18.72288,46.14769],[18.72243,46.14913],[18.72182,46.15311],[18.72312,46.16124],[18.72261,46.16563],[18.71973,46.17666],[18.71847,46.17874],[18.71973,46.18518],[18.72069,46.18607],[18.72517,46.18781],[18.72513,46.1888],[18.72436,46.19206],[18.72366,46.19719],[18.72291,46.20073],[18.7228,46.20213],[18.71236,46.21795],[18.71015,46.22031],[18.70537,46.22336],[18.70534,46.22674],[18.70169,46.23232],[18.6976,46.23658],[18.69236,46.24076],[18.68727,46.24806],[18.68582,46.25103],[18.68451,46.26034],[18.68349,46.26415],[18.68345,46.26632],[18.68316,46.26741],[18.68288,46.26967],[18.68319,46.27456],[18.68271,46.27759],[18.68393,46.28125],[18.68611,46.29106],[18.68582,46.29486],[18.69406,46.30908],[18.69729,46.32148],[18.69836,46.32606],[18.6998,46.33117],[18.69999,46.3345],[18.70111,46.33804],[18.70135,46.34608],[18.70193,46.34714],[18.70192,46.34856]]]}},{"type":"Feature","id":"f4700","properties":{"name":"Szekszard-Alta Ripa","type":"Main Road","certainty":"Conjectured","description":"Passes through Mözs","citation":"Jens Christoffersen","bibliography":"BAtlas 20, Löhberg 2010, Róbert and Máté 2011, Visy 2011","itinerary":"Tabula Peutingeriana, Itinerarium Antonini","lowerDate":100},"geometry":{"type":"MultiLineString","coordinates":[[[18.70192,46.34856],[18.7019,46.35096],[18.70278,46.35266],[18.70383,46.35545],[18.70431,46.36319],[18.70976,46.37835]]]}},{"type":"Feature","id":"f4701","properties":{"name":"Szekszard-Alta Ripa","type":"Main Road","certainty":"Conjectured","description":"Passes through Mözs","citation":"Jens Christoffersen","bibliography":"BAtlas 20, Löhberg 2010, Róbert and Máté 2011, Visy 2011","itinerary":"Tabula Peutingeriana, Itinerarium Antonini","lowerDate":100},"geometry":{"type":"MultiLineString","coordinates":[[[18.70976,46.37835],[18.71156,46.3853],[18.7164,46.40146],[18.71903,46.40402],[18.77246,46.42066],[18.77509,46.422],[18.77975,46.42255],[18.78823,46.42289],[18.79018,46.42367]]]}},{"type":"Feature","id":"f4702","properties":{"name":"Szekszard-Alisca","type":"Secondary Road","certainty":"Conjectured","citation":"Jens Christoffersen","bibliography":"BAtlas 20, Zsolt 2011"},"geometry":{"type":"MultiLineString","coordinates":[[[18.70192,46.34856],[18.7259,46.33862]]]}},{"type":"Feature","id":"f4703","properties":{"name":"Szekszard-Alisca","type":"Secondary Road","certainty":"Certain","citation":"Jens Christoffersen","bibliography":"BAtlas 20, Zsolt 2011"},"geometry":{"type":"MultiLineString","coordinates":[[[18.7259,46.33862],[18.72816,46.33648],[18.73518,46.33215],[18.74415,46.32785],[18.7539,46.32663],[18.76672,46.32492]]]}},{"type":"Feature","id":"f4704","properties":{"name":"Alta Ripa-Lussonium","type":"Main Road","certainty":"Conjectured","citation":"Jens Christoffersen","bibliography":"BAtlas 20, Löhberg 2010, Róbert and Máté 2011, Visy 2011","constructionPeriod":"Severus Alexander (222-235 CE)","itinerary":"Tabula Peutingeriana, Itinerarium Antonini","lowerDate":100},"geometry":{"type":"MultiLineString","coordinates":[[[18.79018,46.42367],[18.78229,46.43208],[18.7831,46.43475],[18.78246,46.43656],[18.77994,46.4409],[18.78007,46.44311],[18.77966,46.4451],[18.78009,46.44717],[18.78148,46.46581],[18.79025,46.50532]]]}},{"type":"Feature","id":"f4705","properties":{"name":"Alta Ripa-Lussonium","type":"Main Road","certainty":"Conjectured","citation":"Jens Christoffersen","bibliography":"BAtlas 20, Löhberg 2010, Róbert and Máté 2011, Visy 2011","constructionPeriod":"Severus Alexander (222-235 CE)","itinerary":"Tabula Peutingeriana, Itinerarium Antonini","lowerDate":100},"geometry":{"type":"MultiLineString","coordinates":[[[18.79025,46.50532],[18.79197,46.50861],[18.80733,46.52883],[18.81872,46.5538],[18.83075,46.5672],[18.84404,46.593],[18.84881,46.60706],[18.8563,46.61667],[18.85957,46.61956],[18.86475,46.62271],[18.8686,46.62699],[18.87459,46.6322],[18.87688,46.63545],[18.87812,46.63861],[18.88006,46.64546],[18.88229,46.64989],[18.88201,46.65257],[18.88189,46.65603]]]}},{"type":"Feature","id":"f4706","properties":{"name":"Lussonium-Annamatia","type":"Main Road","certainty":"Conjectured","citation":"Jens Christoffersen","bibliography":"BAtlas 20, Löhberg 2010, Róbert and Máté 2011, Visy 2011","constructionPeriod":"Caracalla (198-217 CE)","itinerary":"Tabula Peutingeriana, Itinerarium Antonini","lowerDate":100},"geometry":{"type":"MultiLineString","coordinates":[[[18.88189,46.65603],[18.8818,46.65795],[18.88125,46.65838],[18.8813,46.6591],[18.8808,46.65989],[18.88002,46.66175],[18.88056,46.67235],[18.88128,46.67464],[18.88756,46.68475],[18.88813,46.68698],[18.8879,46.68901],[18.88641,46.69387],[18.88672,46.69621],[18.88835,46.7022],[18.88829,46.70664],[18.88401,46.72514],[18.88216,46.73162],[18.88233,46.73544],[18.88407,46.73997],[18.89211,46.75278],[18.89467,46.75983],[18.91112,46.77704],[18.91334,46.78038],[18.91765,46.79277],[18.91835,46.79555],[18.91803,46.80008],[18.9174,46.80217],[18.92113,46.80322],[18.9238,46.8056],[18.92576,46.80656],[18.92128,46.81083],[18.91939,46.81327],[18.91295,46.81878],[18.91009,46.82219],[18.90863,46.82475],[18.90743,46.82816],[18.91013,46.83915],[18.91007,46.84279],[18.91409,46.86],[18.9193,46.86678]]]}},{"type":"Feature","id":"f4707","properties":{"name":"Annamatia-Intercisa","type":"Main Road","certainty":"Conjectured","citation":"Jens Christoffersen","bibliography":"BAtlas 20, Löhberg 2010, Róbert and Máté 2011, Visy 2011","constructionPeriod":"Septimius Severus (193-211 CE)","itinerary":"Tabula Peutingeriana, Itinerarium Antonini","lowerDate":100},"geometry":{"type":"MultiLineString","coordinates":[[[18.9193,46.86678],[18.91923,46.86919],[18.91813,46.88041],[18.92601,46.90957],[18.9307,46.92459],[18.93148,46.92557],[18.93491,46.9427],[18.93681,46.95811],[18.93672,46.96524],[18.93627,46.97382],[18.93631,46.97441],[18.93673,46.97449],[18.9365,46.9759]]]}},{"type":"Feature","id":"f4708","properties":{"name":"Intercisa-Vetus Salina","type":"Main Road","certainty":"Conjectured","description":"Passes by Rácalmás","citation":"Jens Christoffersen","bibliography":"BAtlas 20, Löhberg 2010, Róbert and Máté 2011, Visy 2011","constructionPeriod":"Septimius Severus (193-211 CE)","itinerary":"Tabula Peutingeriana, Itinerarium Antonini","lowerDate":100},"geometry":{"type":"MultiLineString","coordinates":[[[18.9365,46.9759],[18.93654,46.97649],[18.93686,46.97706],[18.93568,46.97802],[18.93488,46.97831],[18.93566,46.97897],[18.93564,46.97926],[18.93351,46.97898],[18.9333,46.97919]]]}},{"type":"Feature","id":"f4709","properties":{"name":"Intercisa-Vetus Salina","type":"Main Road","certainty":"Conjectured","description":"Passes by Rácalmás","citation":"Jens Christoffersen","bibliography":"BAtlas 20, Löhberg 2010, Róbert and Máté 2011, Visy 2011","constructionPeriod":"Septimius Severus (193-211 CE)","itinerary":"Tabula Peutingeriana, Itinerarium Antonini","lowerDate":100},"geometry":{"type":"MultiLineString","coordinates":[[[18.9333,46.97919],[18.93592,46.98089],[18.93718,46.98308],[18.93695,46.98348],[18.93394,46.98489],[18.93195,46.98687],[18.93031,46.9899],[18.92978,46.99297],[18.93037,46.99843],[18.9301,46.99943],[18.93087,47.00296],[18.93041,47.00688],[18.92864,47.01092],[18.91667,47.02691],[18.91313,47.03771],[18.91078,47.04119],[18.90337,47.05095],[18.89112,47.06337],[18.88254,47.07014],[18.87773,47.07767],[18.8764,47.0819],[18.87695,47.08595],[18.88131,47.09801],[18.88185,47.10176],[18.88032,47.10439],[18.87403,47.10835],[18.87158,47.11197],[18.86814,47.12317]]]}},{"type":"Feature","id":"f4741","properties":{"name":"Sopianae-Szekszárd","type":"Secondary Road","certainty":"Conjectured","citation":"Jens Christoffersen","bibliography":"BAtlas 20"},"geometry":{"type":"MultiLineString","coordinates":[[[18.70976,46.37835],[18.69615,46.38031],[18.69254,46.37992],[18.68916,46.3787],[18.67567,46.37647],[18.67203,46.3747],[18.66826,46.37073],[18.66402,46.36883],[18.65861,46.36811],[18.6296,46.36154],[18.62364,46.36137],[18.60812,46.35712],[18.60489,46.35538],[18.59943,46.34988],[18.5918,46.34543],[18.58931,46.34297],[18.58643,46.33799],[18.58259,46.33438],[18.57983,46.33052],[18.56593,46.32035],[18.55923,46.31715],[18.554,46.31296],[18.54623,46.30928],[18.54432,46.30735],[18.543,46.30309],[18.54032,46.29956],[18.53582,46.28936],[18.51801,46.2781],[18.5161,46.2762],[18.51128,46.26442],[18.50888,46.26193],[18.50524,46.26244],[18.49848,46.2601],[18.49544,46.25741],[18.49327,46.2547],[18.48716,46.2529],[18.48592,46.252],[18.48426,46.25193],[18.47922,46.24971],[18.47761,46.24723],[18.47822,46.24469],[18.47882,46.24364],[18.47864,46.241],[18.47905,46.2402],[18.47885,46.23854],[18.47891,46.23743],[18.47811,46.23637],[18.47804,46.23486],[18.4782,46.23376],[18.47766,46.23286],[18.47714,46.23139],[18.47539,46.22974],[18.46926,46.2263],[18.47125,46.22465],[18.46769,46.22031],[18.46049,46.21569],[18.45612,46.21285],[18.45451,46.21105],[18.45238,46.20603],[18.45256,46.2052],[18.45305,46.20422],[18.45303,46.20284],[18.45266,46.2021],[18.45265,46.20178],[18.45329,46.20125],[18.45349,46.20013],[18.45338,46.19977],[18.45268,46.19926],[18.45194,46.19758],[18.44941,46.19449],[18.44926,46.19253],[18.4489,46.19219],[18.4488,46.19193],[18.44989,46.19065],[18.44998,46.18986],[18.44966,46.18966],[18.44947,46.18986],[18.44939,46.19047],[18.44924,46.19059],[18.44895,46.19053],[18.4471,46.18625],[18.44711,46.18419],[18.44751,46.18387],[18.44726,46.18072],[18.43768,46.16484],[18.43417,46.15989],[18.43335,46.15952],[18.43236,46.15987],[18.43136,46.15987],[18.42888,46.15769],[18.42292,46.15797],[18.42208,46.15822]]]}},{"type":"Feature","id":"f4742","properties":{"name":"Sopianae-Szekszárd","type":"Secondary Road","certainty":"Conjectured","citation":"Jens Christoffersen","bibliography":"BAtlas 20"},"geometry":{"type":"MultiLineString","coordinates":[[[18.25291,46.07901],[18.24818,46.07903],[18.2444,46.07837],[18.23974,46.07744],[18.23807,46.07765],[18.23147,46.07658],[18.2281,46.07604]]]}},{"type":"Feature","id":"f4743","properties":{"name":"Sopianae-Szekszárd","type":"Secondary Road","certainty":"Conjectured","citation":"Jens Christoffersen","bibliography":"BAtlas 20"},"geometry":{"type":"MultiLineString","coordinates":[[[18.42208,46.15822],[18.41947,46.15899],[18.41774,46.15838],[18.41606,46.1563],[18.41318,46.15428],[18.40973,46.15034],[18.4077,46.14566],[18.40221,46.14335],[18.39893,46.14263],[18.38996,46.13756],[18.36635,46.13186],[18.34688,46.12526],[18.34535,46.1232],[18.34325,46.1216],[18.31745,46.10891],[18.3039,46.1061],[18.29741,46.10334],[18.2838,46.0934],[18.27847,46.08861],[18.26727,46.08481],[18.25291,46.07901]]]}},{"type":"Feature","id":"f4746","properties":{"name":"Curtae-east","type":"Secondary Road","certainty":"Conjectured","citation":"Jens Christoffersen","bibliography":"BAtlas 20","constructionPeriod":"Valerian (253-260 CE)"},"geometry":{"type":"MultiLineString","coordinates":[[[17.42477,46.41007],[17.42695,46.40999],[17.48102,46.39999],[17.48376,46.3989],[17.49094,46.39806],[17.50009,46.39501],[17.5019,46.39275],[17.50334,46.39199],[17.50787,46.3918],[17.51099,46.3919],[17.51394,46.38947],[17.51621,46.38911],[17.51824,46.3876],[17.52845,46.38961],[17.53046,46.38936],[17.57933,46.36909],[17.61117,46.36316],[17.64753,46.35663],[17.65372,46.35912],[17.67275,46.36307],[17.67396,46.36285],[17.67829,46.3615],[17.70141,46.36596],[17.74525,46.36755],[17.75709,46.36519],[17.76066,46.36622],[17.76495,46.36596],[17.77255,46.36298],[17.77434,46.36246],[17.77652,46.36281],[17.77784,46.36338],[17.7895,46.36519],[17.80361,46.36533],[17.80518,46.36545],[17.80804,46.36539],[17.82198,46.3605],[17.82622,46.36095],[17.83623,46.36486],[17.84948,46.36601],[17.85316,46.36538],[17.87147,46.35921],[17.87655,46.35931],[17.88157,46.36174],[17.9112,46.36801],[17.91599,46.37007],[17.94338,46.36223],[17.97012,46.35467],[18.00265,46.36336],[18.01804,46.36472],[18.04004,46.36974],[18.06739,46.37652],[18.08063,46.37755],[18.09548,46.37573]]]}},{"type":"Feature","id":"f4747","properties":{"name":"Balaton southern road","type":"Secondary Road","certainty":"Conjectured","citation":"Jens Christoffersen","bibliography":"BAtlas 20"},"geometry":{"type":"MultiLineString","coordinates":[[[18.18773,46.99138],[18.18038,46.98607],[18.16444,46.9666],[18.15699,46.95936],[18.14643,46.94116],[18.14007,46.93213],[18.13151,46.92662],[18.09909,46.91285],[18.08121,46.90443],[18.04968,46.89291],[18.03635,46.88871],[18.01708,46.88409],[17.99242,46.88143],[17.9776,46.88092],[17.96531,46.88474],[17.9302,46.876],[17.91222,46.86745],[17.90897,46.86404],[17.87895,46.84937],[17.87813,46.84786],[17.86588,46.84431],[17.85871,46.84128],[17.83992,46.82792],[17.83622,46.82622],[17.83299,46.82561],[17.83001,46.82467],[17.82773,46.82466],[17.8194,46.82586],[17.81667,46.82547],[17.79423,46.81721],[17.78527,46.81219],[17.78215,46.80944],[17.77979,46.80635],[17.77688,46.80524],[17.77283,46.80529],[17.76345,46.80632],[17.72657,46.79582],[17.69408,46.78617],[17.69694,46.78341],[17.69792,46.77935],[17.69767,46.77571],[17.69644,46.77427],[17.6825,46.75391],[17.66904,46.73885],[17.66545,46.73451],[17.67378,46.71537],[17.67604,46.70676],[17.67538,46.70568],[17.65356,46.68462],[17.64427,46.67313],[17.64341,46.66678],[17.64066,46.66703],[17.63898,46.66649],[17.63586,46.66547],[17.63518,46.66481],[17.63519,46.66373],[17.6366,46.65843],[17.63836,46.65671],[17.63941,46.65486],[17.64,46.643],[17.64185,46.64085],[17.64332,46.63119],[17.64293,46.63018],[17.64027,46.62836],[17.63978,46.62695],[17.63839,46.61788],[17.63844,46.61741],[17.63691,46.61561],[17.63725,46.61441],[17.63709,46.6141],[17.63477,46.61295],[17.63332,46.61267],[17.63245,46.61176],[17.63233,46.61095],[17.6334,46.60801],[17.62979,46.60713],[17.62807,46.60523],[17.62786,46.60373],[17.61751,46.6002],[17.60338,46.59074],[17.60205,46.5902],[17.58721,46.58705],[17.57782,46.58392],[17.56734,46.58312],[17.52786,46.57702],[17.5179,46.57482],[17.50971,46.57197],[17.48509,46.56942],[17.45321,46.5851],[17.45015,46.5851],[17.44816,46.5848],[17.44572,46.5851],[17.43243,46.58499],[17.41195,46.58292]]]}},{"type":"Feature","id":"f4756","properties":{"name":"Intercisa-Nagyvenyim","type":"Secondary Road","certainty":"Conjectured","description":"Continues west from Nagyvenyim","citation":"Jens Christoffersen","bibliography":"BAtlas 20","constructionPeriod":"Decius (249-251 CE)"},"geometry":{"type":"MultiLineString","coordinates":[[[18.9333,46.97919],[18.93101,46.97763],[18.93074,46.97796],[18.93088,46.97836],[18.93097,46.97879],[18.93051,46.97907],[18.9282,46.9794],[18.92603,46.97922],[18.92413,46.97884],[18.92267,46.97902],[18.92084,46.97778],[18.91032,46.974],[18.90916,46.97396],[18.90825,46.97277],[18.90645,46.97271],[18.90389,46.97208],[18.87225,46.95974],[18.85501,46.9552],[18.83131,46.94536],[18.82724,46.9442],[18.82374,46.9438],[18.81487,46.9435],[18.81207,46.94284],[18.80929,46.94151],[18.80453,46.93921],[18.79559,46.93326],[18.76477,46.91906],[18.7622,46.91747],[18.74988,46.9145],[18.73231,46.90754],[18.70942,46.89843],[18.70888,46.89774],[18.7093,46.89511],[18.70897,46.89449],[18.68208,46.88156],[18.67813,46.87854],[18.67678,46.87637],[18.67643,46.87499],[18.63667,46.86121],[18.63546,46.86036],[18.63101,46.85877]]]}},{"type":"Feature","id":"f4757","properties":{"name":"Intercisa-Nagyvenyim","type":"Secondary Road","certainty":"Conjectured","description":"Continues west from Nagyvenyim","citation":"Jens Christoffersen","bibliography":"BAtlas 20","constructionPeriod":"Decius (249-251 CE)"},"geometry":{"type":"MultiLineString","coordinates":[[[18.63101,46.85877],[18.6268,46.85558],[18.60403,46.85031],[18.58024,46.85344],[18.5796,46.85326],[18.57503,46.85164],[18.56496,46.84813],[18.56402,46.84746],[18.56327,46.84656],[18.56008,46.84407],[18.55932,46.84374],[18.54753,46.84118],[18.53302,46.83679],[18.52795,46.83617],[18.52575,46.83584],[18.5221,46.83435],[18.5219,46.83402],[18.52182,46.83335],[18.52144,46.83323],[18.52012,46.83318],[18.51976,46.83287],[18.51936,46.83235],[18.51737,46.83186]]]}},{"type":"Feature","id":"f4760","properties":{"name":"Gorsium-south","type":"Secondary Road","certainty":"Conjectured","citation":"Jens Christoffersen","bibliography":"BAtlas 20, Löhberg 2010","itinerary":"Itinerarium Antonini"},"geometry":{"type":"MultiLineString","coordinates":[[[18.41956,47.09129],[18.42832,47.06438],[18.4387,47.04583],[18.44527,47.02618],[18.44634,47.02553],[18.44804,47.02386],[18.45124,47.01977],[18.45186,47.0187],[18.45267,47.01624],[18.45719,47.00917],[18.46177,47.00768],[18.4627,47.00733],[18.4634,47.00681],[18.46388,47.00597],[18.46392,47.0052],[18.46455,47.0042],[18.4632,47.00106],[18.48746,46.96006],[18.48913,46.9582],[18.48438,46.95581],[18.48271,46.95357],[18.47537,46.94864],[18.4754,46.94355],[18.46713,46.92763],[18.47475,46.88987],[18.4913,46.87382],[18.50133,46.85969],[18.50643,46.84899],[18.51505,46.8367],[18.51737,46.83186]]]}},{"type":"Feature","id":"f4761","properties":{"name":"Gorsium-south","type":"Secondary Road","certainty":"Conjectured","citation":"Jens Christoffersen","bibliography":"BAtlas 20, Löhberg 2010","itinerary":"Itinerarium Antonini"},"geometry":{"type":"MultiLineString","coordinates":[[[18.35525,46.53845],[18.35603,46.53802],[18.35777,46.53599],[18.35829,46.53471],[18.36018,46.53244],[18.36096,46.53178],[18.36233,46.53141],[18.36353,46.52996],[18.36796,46.52805],[18.37483,46.52638],[18.37802,46.52478],[18.38002,46.52439],[18.38268,46.52421],[18.38821,46.52531],[18.39615,46.50953],[18.39425,46.50639],[18.37842,46.49519],[18.37682,46.49366],[18.37096,46.48208],[18.36979,46.47878],[18.36768,46.47727],[18.36694,46.4761],[18.36506,46.47458],[18.36298,46.47374],[18.36173,46.47274],[18.35916,46.47205],[18.35787,46.47133],[18.355,46.46869],[18.3493,46.46674],[18.34394,46.46627],[18.34235,46.46572],[18.33747,46.46476],[18.32231,46.45834],[18.31983,46.45503],[18.31944,46.45339],[18.32031,46.45024],[18.32017,46.44917],[18.31974,46.44848],[18.31995,46.44775],[18.31964,46.44763],[18.31534,46.44785],[18.3145,46.44844],[18.3104,46.44667],[18.30584,46.44744],[18.29259,46.44512],[18.2756,46.44785],[18.27101,46.44733],[18.269,46.44639],[18.26258,46.44598],[18.25817,46.44662],[18.25496,46.44512],[18.25283,46.44464],[18.24813,46.44247],[18.24499,46.44184],[18.24317,46.44096],[18.24152,46.43885],[18.24056,46.43573],[18.24082,46.43246],[18.24022,46.43098],[18.23718,46.42865],[18.23494,46.42748],[18.23415,46.42561],[18.22547,46.42295],[18.22408,46.42381],[18.22229,46.42577],[18.22172,46.42624],[18.21909,46.42686],[18.21408,46.42672],[18.20321,46.42179],[18.18555,46.41712],[18.17826,46.40965],[18.15921,46.40199],[18.15337,46.39844],[18.14743,46.3954],[18.14201,46.38687],[18.13761,46.38584],[18.13521,46.38535],[18.13103,46.38322],[18.13085,46.37779],[18.12958,46.36934],[18.1276,46.36649],[18.12764,46.3658],[18.1282,46.3647],[18.12795,46.36386],[18.12743,46.36318],[18.12573,46.36155],[18.12542,46.3608],[18.12553,46.3598],[18.1265,46.35664],[18.1269,46.33652],[18.12519,46.33626],[18.12474,46.33594],[18.12442,46.33523],[18.12382,46.33488],[18.1212,46.33459]]]}},{"type":"Feature","id":"f4762","properties":{"name":"Gorsium-south","type":"Secondary Road","certainty":"Conjectured","citation":"Jens Christoffersen","bibliography":"BAtlas 20, Löhberg 2010","itinerary":"Itinerarium Antonini"},"geometry":{"type":"MultiLineString","coordinates":[[[18.51737,46.83186],[18.52107,46.82148],[18.53494,46.79966],[18.53963,46.79063],[18.53963,46.78252],[18.5413,46.75744],[18.53837,46.75518],[18.53636,46.75325],[18.53004,46.74835],[18.52698,46.74701],[18.51754,46.74488],[18.47724,46.72901],[18.43721,46.69319],[18.43284,46.68912],[18.4315,46.68754],[18.43056,46.68514],[18.42964,46.67688],[18.42868,46.67268],[18.42701,46.67017],[18.4115,46.65645],[18.40921,46.65366],[18.4087,46.65057],[18.408,46.61351],[18.40779,46.60333],[18.40318,46.59541],[18.40303,46.59507],[18.40367,46.594],[18.40262,46.58915],[18.40173,46.58675],[18.40126,46.58583],[18.40032,46.58487],[18.40018,46.58349],[18.39637,46.57981],[18.39486,46.57928],[18.39403,46.57883],[18.39287,46.57851],[18.39076,46.57851],[18.39016,46.5759],[18.38048,46.57206],[18.3786,46.57183],[18.37418,46.56952],[18.37161,46.5659],[18.37031,46.56135],[18.36866,46.55918],[18.36869,46.55812],[18.36837,46.55721],[18.36424,46.55275],[18.36133,46.54334],[18.36098,46.54255],[18.35525,46.53845]]]}},{"type":"Feature","id":"f4763","properties":{"name":"Enying connecting road","type":"Secondary Road","certainty":"Conjectured","citation":"Jens Christoffersen","bibliography":"BAtlas 20"},"geometry":{"type":"MultiLineString","coordinates":[[[18.35525,46.53845],[18.35026,46.54113],[18.32153,46.57266],[18.31757,46.58081],[18.31552,46.58341],[18.3144,46.58667],[18.31439,46.58751],[18.31328,46.59016],[18.31277,46.59221],[18.30979,46.59671],[18.30776,46.60222],[18.30705,46.60327],[18.30618,46.60414],[18.30418,46.60534],[18.30351,46.60599],[18.30236,46.61083],[18.30003,46.61406],[18.29862,46.61652],[18.29657,46.61829],[18.2959,46.61962],[18.29297,46.62344],[18.29054,46.62506],[18.28828,46.62632],[18.28368,46.63043],[18.28301,46.63073],[18.28213,46.63096],[18.28152,46.63228],[18.2816,46.63284],[18.28161,46.63391],[18.28179,46.63559],[18.28141,46.63649],[18.28077,46.63721],[18.27995,46.63876],[18.27244,46.65924],[18.27007,46.66247],[18.26871,46.66303],[18.26895,46.66407],[18.27139,46.67181],[18.27635,46.67769],[18.27873,46.6838],[18.2821,46.71322],[18.28719,46.7242],[18.28641,46.72877],[18.28579,46.73727],[18.28562,46.73847],[18.28612,46.74161],[18.28601,46.74302],[18.28285,46.75062],[18.28245,46.75112],[18.28098,46.75248],[18.28044,46.75326],[18.28034,46.75431],[18.2808,46.75559],[18.28071,46.75659],[18.28009,46.75745],[18.2798,46.75838],[18.27971,46.7592],[18.28046,46.76181],[18.28055,46.76237],[18.28026,46.76406],[18.28025,46.7648],[18.28072,46.76566],[18.28063,46.76645],[18.27798,46.77309],[18.27683,46.77737],[18.27683,46.78365],[18.27845,46.78546],[18.28576,46.79046],[18.28728,46.79186],[18.28742,46.79653],[18.28412,46.81553],[18.28354,46.81612],[18.28357,46.81865],[18.28174,46.82338],[18.28499,46.82456],[18.28571,46.82525],[18.286,46.82584],[18.28604,46.82614],[18.28635,46.82643],[18.28575,46.8267],[18.27919,46.82825],[18.27614,46.82949],[18.27151,46.8303],[18.26983,46.83115],[18.267,46.834],[18.26504,46.83738],[18.26476,46.83804],[18.26472,46.83853],[18.26481,46.83935],[18.26616,46.84439],[18.26621,46.84501],[18.26601,46.84587],[18.26481,46.84771],[18.26476,46.84874],[18.26606,46.85266],[18.26669,46.85386],[18.26934,46.85705],[18.27265,46.86321],[18.27281,46.86375],[18.27271,46.86455],[18.27076,46.86956],[18.26716,46.87342],[18.26663,46.87447],[18.26648,46.87521],[18.2666,46.87604],[18.26718,46.87698],[18.26863,46.87841],[18.26925,46.87916],[18.26953,46.88005],[18.26948,46.88091],[18.26793,46.88429],[18.26638,46.88807],[18.26472,46.91382],[18.26417,46.91608],[18.25921,46.92175],[18.24609,46.92628],[18.24463,46.92737],[18.24294,46.9295]]]}},{"type":"Feature","id":"f4767","properties":{"name":"Sopianae-Tricciana","type":"Secondary Road","certainty":"Conjectured","description":"Passes through Iovia. Continues north after Tricciana","citation":"Jens Christoffersen","bibliography":"BAtlas 20, Löhberg 2010","itinerary":"Itinerarium Antonini"},"geometry":{"type":"MultiLineString","coordinates":[[[18.2281,46.07604],[18.22879,46.07752],[18.23155,46.07756],[18.23561,46.07923],[18.23736,46.07927],[18.24192,46.0804],[18.24523,46.08262],[18.24766,46.08567],[18.25123,46.08874],[18.25197,46.09076],[18.25461,46.09118],[18.25756,46.09407],[18.25975,46.09716],[18.26034,46.09842],[18.2593,46.09968],[18.25898,46.10046],[18.2599,46.1015],[18.2607,46.10185],[18.26015,46.10462],[18.25943,46.10714],[18.25913,46.10931],[18.2593,46.11185],[18.2599,46.1128],[18.26028,46.1135],[18.26033,46.11502],[18.26087,46.11527],[18.26115,46.11751],[18.26127,46.12111],[18.26154,46.12202],[18.26094,46.123],[18.2592,46.12525],[18.25774,46.1265],[18.25492,46.12773],[18.25249,46.13018],[18.25164,46.13345],[18.25063,46.13523],[18.25051,46.13643],[18.25073,46.13914],[18.25062,46.14035],[18.24911,46.14183],[18.2492,46.14291],[18.24966,46.14444],[18.25003,46.14519],[18.24939,46.14672],[18.24785,46.14789],[18.24673,46.14813],[18.24523,46.14784],[18.24495,46.1474],[18.24501,46.14669],[18.24463,46.14635],[18.244,46.1464],[18.24312,46.14764],[18.24391,46.14922],[18.24352,46.15054],[18.24398,46.15222],[18.2439,46.1529],[18.24286,46.15445],[18.24301,46.1563],[18.24237,46.15676],[18.23957,46.15723],[18.23839,46.15733],[18.23805,46.15772],[18.23808,46.15805],[18.23857,46.15824],[18.23977,46.15803],[18.24036,46.15829],[18.24032,46.1587],[18.2392,46.15936],[18.23875,46.16039],[18.23823,46.16071],[18.23765,46.16072],[18.23699,46.16041],[18.23629,46.15986],[18.23565,46.15982],[18.23486,46.16016],[18.23436,46.16055],[18.2334,46.16067],[18.23215,46.16052],[18.22968,46.16079],[18.22817,46.16045],[18.22664,46.1599],[18.22539,46.1599],[18.21993,46.16096],[18.21624,46.16083],[18.21555,46.1611],[18.21524,46.16147],[18.21512,46.16233],[18.21515,46.16405],[18.21557,46.16544],[18.2154,46.16657],[18.21508,46.16752],[18.21364,46.17017],[18.21228,46.17161],[18.21067,46.17629],[18.21011,46.17739],[18.20906,46.18115],[18.20817,46.18248],[18.19889,46.19449],[18.19697,46.19633],[18.19601,46.19808],[18.19527,46.19904],[18.19417,46.20256],[18.19407,46.20488],[18.19347,46.20692],[18.18913,46.21064],[18.18615,46.21067],[18.18519,46.21045],[18.18115,46.21015],[18.17939,46.20962],[18.17876,46.20965],[18.17619,46.21097],[18.17389,46.21316],[18.17293,46.21377],[18.17186,46.21404],[18.14065,46.21408],[18.12834,46.21532],[18.12346,46.21713],[18.12311,46.21758],[18.12297,46.22047],[18.12103,46.22198],[18.12184,46.2252],[18.1205,46.24725],[18.11926,46.25011],[18.11348,46.25191],[18.10657,46.25275],[18.1063,46.25306],[18.10548,46.25911],[18.10605,46.26281],[18.1046,46.26477],[18.10366,46.27161],[18.10386,46.27225],[18.10786,46.27851],[18.10917,46.28013],[18.11151,46.28273],[18.1184,46.2862],[18.12335,46.29636],[18.13126,46.30564],[18.13192,46.30891],[18.13223,46.31886],[18.12687,46.32779],[18.1212,46.33459]]]}},{"type":"Feature","id":"f4768","properties":{"name":"Sopianae-Tricciana","type":"Secondary Road","certainty":"Conjectured","description":"Passes through Iovia. Continues north after Tricciana","citation":"Jens Christoffersen","bibliography":"BAtlas 20, Löhberg 2010","itinerary":"Itinerarium Antonini"},"geometry":{"type":"MultiLineString","coordinates":[[[18.1212,46.33459],[18.11969,46.33637],[18.11698,46.34251],[18.11296,46.34715],[18.10806,46.35156],[18.10367,46.35842],[18.10574,46.36025],[18.10048,46.36623],[18.09785,46.37197],[18.09548,46.37573]]]}},{"type":"Feature","id":"f4769","properties":{"name":"Sopianae-Tricciana","type":"Secondary Road","certainty":"Conjectured","description":"Passes through Iovia. Continues north after Tricciana","citation":"Jens Christoffersen","bibliography":"BAtlas 20, Löhberg 2010","itinerary":"Itinerarium Antonini"},"geometry":{"type":"MultiLineString","coordinates":[[[18.09548,46.37573],[18.09378,46.37843],[18.0902,46.39294],[18.08489,46.41254],[18.08367,46.41984],[18.08877,46.43285],[18.08993,46.43595],[18.09498,46.44955],[18.09483,46.4596],[18.09386,46.46955],[18.10095,46.47755],[18.12522,46.49034],[18.12646,46.49188],[18.13026,46.49187],[18.13203,46.49985],[18.12872,46.5103],[18.11975,46.52818],[18.12167,46.5313],[18.12322,46.53598],[18.12593,46.53567],[18.13531,46.53851],[18.14436,46.54639],[18.14917,46.54755],[18.16608,46.56016],[18.17438,46.56946],[18.17261,46.57162],[18.17254,46.57322],[18.17134,46.57597],[18.16812,46.57962],[18.16645,46.58127],[18.16665,46.5822],[18.16645,46.58289],[18.16076,46.58669],[18.16086,46.58897],[18.15776,46.59285],[18.14849,46.59983],[18.14479,46.60317],[18.14157,46.60754],[18.13992,46.60824],[18.13605,46.60888],[18.13417,46.61093],[18.13055,46.61393],[18.12309,46.6158],[18.12071,46.61614],[18.11986,46.61666],[18.10586,46.62075],[18.10156,46.625],[18.10073,46.62498],[18.08711,46.62907],[18.076,46.63375],[18.0723,46.63696],[18.07131,46.63953],[18.06993,46.64073],[18.06963,46.64274],[18.06835,46.64395],[18.0654,46.64505],[18.0633,46.64572],[18.06066,46.64949],[18.05976,46.65134],[18.05948,46.65852],[18.05433,46.66908],[18.05245,46.67121],[18.05133,46.67872],[18.05228,46.68105],[18.05086,46.68775],[18.05094,46.68811],[18.06075,46.6906],[18.06515,46.69237],[18.06629,46.69341],[18.06732,46.69378],[18.06816,46.69587],[18.07253,46.69679],[18.0784,46.69806],[18.08595,46.69841],[18.08167,46.70795],[18.07652,46.71167],[18.07445,46.71859],[18.0766,46.71891],[18.07754,46.7181],[18.07876,46.71814],[18.07845,46.71884],[18.07883,46.71949],[18.08853,46.7227],[18.09231,46.72486],[18.09339,46.72734],[18.09292,46.72869],[18.09047,46.7307],[18.08947,46.73225],[18.08771,46.73327],[18.08764,46.73378],[18.08775,46.73718],[18.08815,46.73753],[18.08846,46.73883],[18.08961,46.74006],[18.09028,46.7401],[18.09135,46.73982],[18.09294,46.74003],[18.09526,46.74105],[18.10256,46.74342],[18.1017,46.74476],[18.09981,46.74702],[18.09887,46.7469],[18.09847,46.74689],[18.09692,46.75035],[18.09477,46.75392],[18.09463,46.75515],[18.09423,46.7558],[18.09816,46.75677],[18.09913,46.7578],[18.09919,46.75827],[18.09862,46.75934],[18.09695,46.76731],[18.09812,46.77604],[18.09572,46.78129],[18.09626,46.78287],[18.09858,46.78868],[18.09922,46.78956],[18.10058,46.79022],[18.10883,46.79231],[18.10876,46.79421],[18.1076,46.79596],[18.1068,46.79643],[18.1063,46.79761],[18.10679,46.79857],[18.10637,46.79996],[18.10702,46.80061],[18.10562,46.80174],[18.1087,46.8034],[18.1089,46.80405],[18.10875,46.80499],[18.10892,46.80687],[18.10762,46.81453],[18.10767,46.81534],[18.10878,46.81785],[18.10898,46.81971],[18.10748,46.82346],[18.10741,46.82429],[18.10872,46.82605],[18.10948,46.82773],[18.10975,46.83043],[18.10445,46.83231],[18.10186,46.83645],[18.10151,46.83771],[18.10366,46.83863],[18.12436,46.84396],[18.14797,46.8558],[18.14912,46.85596],[18.15357,46.85737],[18.15665,46.85689],[18.15781,46.85704],[18.16267,46.85904],[18.16488,46.85949],[18.1636,46.86314],[18.18916,46.873],[18.19509,46.88425],[18.20253,46.8944],[18.20484,46.90759],[18.21996,46.91278],[18.23644,46.91708],[18.23799,46.91839],[18.23855,46.91981],[18.23803,46.92387],[18.23828,46.92438],[18.24022,46.92489],[18.23968,46.92669],[18.23983,46.92797],[18.24034,46.92853],[18.24294,46.9295]]]}},{"type":"Feature","id":"f4770","properties":{"name":"Silicenis-Sopianae","type":"Secondary Road","certainty":"Conjectured","description":"Passes through Limusa","citation":"Jens Christoffersen","bibliography":"BAtlas 20, Löhberg 2010","constructionPeriod":"Gordian III (238-244 CE)","itinerary":"Itinerarium Antonini"},"geometry":{"type":"MultiLineString","coordinates":[[[18.2281,46.07604],[18.21585,46.0732],[18.20811,46.07079],[18.20667,46.06985],[18.20276,46.06893],[18.19234,46.06538],[18.18092,46.06474],[18.17292,46.06508],[18.16688,46.06505],[18.1619,46.06517],[18.15478,46.06365]]]}},{"type":"Feature","id":"f4772","properties":{"name":"Silicenis-Sopianae","type":"Secondary Road","certainty":"Conjectured","description":"Passes through Limusa","citation":"Jens Christoffersen","bibliography":"BAtlas 20, Löhberg 2010","constructionPeriod":"Gordian III (238-244 CE)","itinerary":"Itinerarium Antonini"},"geometry":{"type":"MultiLineString","coordinates":[[[18.05852,46.0485],[18.05018,46.04278],[18.02557,46.0317],[18.02002,46.03216],[17.98642,46.04029],[17.98586,46.04068],[17.98568,46.04121],[17.98568,46.04287]]]}},{"type":"Feature","id":"f4774","properties":{"name":"Silicenis-Sopianae","type":"Secondary Road","certainty":"Conjectured","description":"Passes through Limusa","citation":"Jens Christoffersen","bibliography":"BAtlas 20, Löhberg 2010","constructionPeriod":"Gordian III (238-244 CE)","itinerary":"Itinerarium Antonini"},"geometry":{"type":"MultiLineString","coordinates":[[[18.15478,46.06365],[18.1481,46.06223],[18.13821,46.06158],[18.12242,46.06198],[18.07772,46.05246],[18.0685,46.05194],[18.05852,46.0485]]]}},{"type":"Feature","id":"f4777","properties":{"name":"Cserdi-east","type":"Secondary Road","certainty":"Conjectured","citation":"Jens Christoffersen","bibliography":"BAtlas 20, Szabó 2013"},"geometry":{"type":"MultiLineString","coordinates":[[[17.99045,46.08186],[17.99083,46.08049],[17.99079,46.07888],[17.99193,46.07746],[17.99352,46.0763],[18.00282,46.07434],[18.00976,46.0765],[18.01547,46.07737],[18.02813,46.07685],[18.04802,46.07259],[18.0499,46.07044],[18.05136,46.05857],[18.0531,46.05341],[18.05852,46.0485]]]}},{"type":"Feature","id":"f4779","properties":{"name":"Sopianae-southwest","type":"Secondary Road","certainty":"Conjectured","citation":"Jens Christoffersen","bibliography":"BAtlas 20"},"geometry":{"type":"MultiLineString","coordinates":[[[17.968,45.75204],[17.96827,45.75979],[17.97313,45.77858],[17.97168,45.79465],[17.96411,45.80911],[17.96446,45.80982],[17.9661,45.81537],[17.96661,45.81589],[17.97144,45.82786],[17.97301,45.82912],[17.97254,45.83054],[17.97246,45.83296],[17.97506,45.83886],[17.97512,45.83925],[17.97443,45.83987],[17.97427,45.84011],[17.97533,45.84151],[17.97668,45.84226],[17.98268,45.85498],[17.98241,45.85614],[17.98227,45.85868],[17.98238,45.86004],[17.9832,45.85991],[17.984,45.85943],[17.9856,45.86046],[18.01106,45.89209],[18.01184,45.89255],[18.01589,45.89314],[18.03219,45.89213],[18.03338,45.8924],[18.039,45.89506],[18.03966,45.89564],[18.04022,45.89666],[18.04074,45.90197],[18.04128,45.90272],[18.04226,45.90333],[18.04451,45.90388],[18.04542,45.90443],[18.04604,45.90525],[18.04617,45.90623],[18.04644,45.90674],[18.07699,45.9437],[18.07874,45.9462],[18.08118,45.94833],[18.0853,45.95023],[18.08792,45.95232],[18.08844,45.95311],[18.08864,45.95442],[18.08895,45.95534],[18.08863,45.95647],[18.08889,45.95698],[18.09255,45.95875],[18.11368,45.96427],[18.12702,45.96829],[18.12766,45.9686],[18.12853,45.96968],[18.1293,45.96991],[18.13584,45.96973],[18.13784,45.97437],[18.15097,45.98238],[18.15174,45.98305],[18.15212,45.98373],[18.1537,45.99194],[18.15399,45.99259],[18.15985,45.99945],[18.1601,46.00007],[18.16007,46.00625],[18.15975,46.0085],[18.16113,46.01777],[18.16083,46.02069],[18.15855,46.02838],[18.15569,46.03715],[18.15432,46.03918],[18.15385,46.04043],[18.15471,46.04253],[18.15475,46.06069],[18.15478,46.06365]]]}},{"type":"Feature","id":"f4780","properties":{"name":"Gorsium-Alta Ripa","type":"Secondary Road","certainty":"Conjectured","description":"Reaches Gorsium by the northern connection","citation":"Jens Christoffersen","bibliography":"BAtlas 20"},"geometry":{"type":"MultiLineString","coordinates":[[[18.79025,46.50532],[18.79023,46.50591],[18.77565,46.52027],[18.76876,46.52697],[18.76727,46.52936],[18.76616,46.52965],[18.76086,46.53344],[18.7502,46.55006],[18.7411,46.55009],[18.73704,46.55093],[18.72995,46.55947],[18.73024,46.56036],[18.72982,46.56866],[18.72743,46.57596],[18.726,46.5787],[18.72157,46.59125],[18.72088,46.5928],[18.7195,46.59461],[18.71841,46.59709],[18.71829,46.59803],[18.71687,46.60128],[18.71605,46.60273],[18.71477,46.60283],[18.70919,46.61316],[18.70306,46.62164],[18.70026,46.62555],[18.69759,46.62935],[18.69771,46.62988],[18.6969,46.63178],[18.69494,46.63384],[18.69401,46.63577],[18.69374,46.63708],[18.69394,46.63948],[18.69302,46.64143],[18.69152,46.64334],[18.68938,46.64698],[18.68738,46.65016],[18.68818,46.65091],[18.68865,46.65139],[18.6898,46.65175],[18.69175,46.65274],[18.6861,46.65992],[18.68561,46.66029],[18.68479,46.66022],[18.68441,46.6606],[18.68269,46.6609],[18.68233,46.66119],[18.68042,46.66402],[18.67854,46.66551],[18.67421,46.6701],[18.672,46.67227],[18.66946,46.67332],[18.66764,46.67545],[18.66581,46.6786],[18.66572,46.679],[18.66793,46.68023],[18.66894,46.68235],[18.67188,46.6865],[18.67307,46.69388],[18.67276,46.69603],[18.6711,46.69941],[18.66831,46.70261],[18.66756,46.70414],[18.66745,46.70584],[18.66612,46.71099],[18.66614,46.71245],[18.66555,46.71335],[18.66534,46.71489],[18.66486,46.71602],[18.66468,46.71813],[18.66338,46.71962],[18.66076,46.7247],[18.66002,46.72715],[18.65814,46.73109],[18.65803,46.73327],[18.6571,46.73646],[18.65649,46.73774],[18.65566,46.73877],[18.64527,46.74641],[18.63648,46.76059],[18.63532,46.76316],[18.63424,46.76397],[18.63217,46.76481],[18.63093,46.7664],[18.62862,46.76964],[18.62749,46.77061],[18.6298,46.77127],[18.62967,46.77172],[18.63344,46.77882],[18.63488,46.78491],[18.63956,46.8086],[18.63949,46.80977],[18.64082,46.81375],[18.64061,46.81475],[18.63893,46.81701],[18.63662,46.82429],[18.63629,46.82897],[18.63659,46.83139],[18.63574,46.83909],[18.63561,46.84436],[18.63441,46.84878],[18.63311,46.85211],[18.63101,46.85877]]]}},{"type":"Feature","id":"f4781","properties":{"name":"Gorsium-Alta Ripa","type":"Secondary Road","certainty":"Conjectured","description":"Reaches Gorsium by the northern connection","citation":"Jens Christoffersen","bibliography":"BAtlas 20"},"geometry":{"type":"MultiLineString","coordinates":[[[18.63101,46.85877],[18.63014,46.86169],[18.62687,46.86696],[18.62594,46.87094],[18.62563,46.87483],[18.6204,46.8855],[18.61848,46.88868],[18.61372,46.89886],[18.61372,46.89982],[18.61224,46.90103],[18.60592,46.91606],[18.60285,46.92035],[18.60246,46.92177],[18.59802,46.93328],[18.59545,46.93713],[18.5922,46.94573],[18.59107,46.94739],[18.57247,46.97139],[18.55311,47.0089],[18.54637,47.01742],[18.51698,47.06246],[18.50391,47.07886],[18.47887,47.10312]]]}},{"type":"Feature","id":"f4796","properties":{"name":"Florentia-Dacia","type":"Secondary Road","certainty":"Conjectured","description":"Passes through Contra Florentiam and continues east to Dacia","citation":"Jens Christoffersen","bibliography":"BAtlas 20"},"geometry":{"type":"MultiLineString","coordinates":[[[18.75867,46.08708],[18.75892,46.0869],[18.76043,46.08452],[18.76162,46.08433],[18.76235,46.08408],[18.76646,46.0809],[18.7672,46.08151],[18.76767,46.08204],[18.76847,46.08249],[18.76968,46.08267],[18.77249,46.08257],[18.77541,46.08298],[18.77918,46.0823],[18.79378,46.07636],[18.80317,46.0695],[18.81898,46.06494],[18.82699,46.06648],[18.82755,46.06507],[18.84136,46.07297],[18.84101,46.07616],[18.88873,46.08366],[18.8913,46.08316],[18.89431,46.08051],[18.90082,46.0802],[18.92548,46.08617],[18.92665,46.097],[18.92998,46.1016],[18.93026,46.1026],[18.92953,46.10391],[18.92565,46.10719],[18.92789,46.10736],[18.93022,46.10808],[18.94799,46.10581],[18.96536,46.10498],[18.97148,46.10613],[18.97838,46.10601],[18.98287,46.10633],[18.98933,46.10768],[18.98595,46.11317],[19.00051,46.11645],[19.00846,46.11762],[19.03456,46.12364],[19.03603,46.12476],[19.0402,46.12568],[19.03847,46.12979],[19.05639,46.15095],[19.07166,46.14743],[19.11426,46.13453],[19.12746,46.13229],[19.14994,46.12556],[19.15954,46.12505],[19.16283,46.12657],[19.16782,46.12746],[19.17819,46.1283],[19.19332,46.13289],[19.21214,46.1364],[19.273,46.164],[19.28338,46.1649],[19.29138,46.16952],[19.2924,46.17096],[19.29259,46.17328],[19.29875,46.17496],[19.29822,46.17627],[19.3048,46.17832],[19.30994,46.18038],[19.33384,46.19035],[19.3728,46.21297],[19.37664,46.21453],[19.37885,46.21349],[19.38473,46.21674],[19.44126,46.23963],[19.44656,46.24511],[19.46439,46.25765],[19.49899,46.27166],[19.56828,46.27398],[19.60667,46.26147],[19.64917,46.25217],[19.65794,46.25539],[19.65732,46.25622],[19.65741,46.25677],[19.66341,46.26533],[19.68336,46.28074],[19.68766,46.27806],[19.69083,46.2772],[19.69892,46.27228],[19.69992,46.27199],[19.70121,46.27226],[19.71841,46.28549],[19.72014,46.28609],[19.7321,46.28716],[19.73901,46.28952],[19.74465,46.29023],[19.74532,46.29079],[19.75002,46.2892],[19.74999,46.28811],[19.75071,46.2827],[19.75762,46.27328],[19.75837,46.27275],[19.75943,46.27246],[19.7651,46.27234],[19.76979,46.2705],[19.77775,46.27122],[19.78165,46.27386],[19.78767,46.27643],[19.78924,46.27757],[19.80331,46.28304],[19.84495,46.28824],[19.8532,46.28744],[19.85697,46.28792],[19.85941,46.287],[19.867,46.28698],[19.87496,46.28544],[19.88181,46.28652],[19.88757,46.28645],[19.88997,46.2868],[19.89432,46.28661],[19.9004,46.28385],[19.90826,46.28247],[19.91268,46.27994],[19.91554,46.27888],[19.91856,46.27845],[19.92174,46.27733],[19.92491,46.27663],[19.92754,46.27491],[19.9367,46.27335],[19.93784,46.27273],[19.93895,46.27193],[19.94006,46.27167],[19.94829,46.27221],[19.95354,46.27378],[19.96127,46.27439],[19.9812,46.2724],[19.9817,46.2721],[19.9846,46.26898],[19.98551,46.26845],[19.99967,46.26353],[20.00372,46.26024],[20.01145,46.2568],[20.01524,46.25391],[20.02192,46.25223],[20.0248,46.25267],[20.02598,46.25248],[20.02701,46.25198],[20.0299,46.24941],[20.03135,46.24726],[20.0336,46.24738],[20.04039,46.24714],[20.0461,46.2496],[20.06507,46.25247],[20.07913,46.25163],[20.10847,46.25504],[20.11445,46.25406],[20.13037,46.25321],[20.1386,46.25194],[20.13957,46.25496],[20.14069,46.25598],[20.14583,46.25381]]]}},{"type":"Feature","id":"f4797","properties":{"name":"Florentia-Szebény","type":"Secondary Road","certainty":"Conjectured","description":"Continues west","citation":"Jens Christoffersen","bibliography":"BAtlas 20"},"geometry":{"type":"MultiLineString","coordinates":[[[18.75872,46.08272],[18.7575,46.08251],[18.75515,46.08248],[18.75401,46.08166],[18.75173,46.07902],[18.73362,46.07469],[18.73252,46.07429],[18.72849,46.07329],[18.72773,46.07344],[18.72691,46.07427],[18.72457,46.07418],[18.71194,46.0747],[18.70921,46.07562],[18.70695,46.07701],[18.69829,46.08121],[18.68465,46.08078],[18.67748,46.08012],[18.67634,46.07972],[18.67464,46.08075],[18.66938,46.08195],[18.66531,46.08118],[18.66299,46.07983],[18.65989,46.08034],[18.65883,46.08111],[18.65828,46.08081],[18.65675,46.08364],[18.65558,46.08577],[18.65458,46.08655],[18.65178,46.08984],[18.65153,46.09038],[18.63401,46.0946],[18.63139,46.09424],[18.62905,46.09248],[18.62375,46.09344],[18.61903,46.10066],[18.61321,46.10426],[18.6109,46.10803],[18.60544,46.12207],[18.60509,46.12192],[18.60293,46.12334],[18.60086,46.12373],[18.59925,46.12462],[18.59788,46.12489],[18.59699,46.12467],[18.59635,46.12494],[18.595,46.12617],[18.59231,46.12676],[18.59094,46.12738],[18.58995,46.12746],[18.5878,46.12921],[18.58633,46.13141],[18.58318,46.13275],[18.58027,46.135],[18.57678,46.13513],[18.57162,46.13624],[18.56389,46.14016],[18.55702,46.14101],[18.55506,46.14163],[18.54572,46.14068],[18.53837,46.13765],[18.53491,46.13503],[18.53233,46.13399],[18.52763,46.12834],[18.52634,46.12663],[18.51881,46.12305],[18.51463,46.11893],[18.50377,46.11228],[18.49139,46.10833],[18.49088,46.109],[18.48921,46.10951],[18.48625,46.10975],[18.48645,46.10765],[18.48586,46.1065],[18.48433,46.10549],[18.47676,46.10179],[18.4761,46.10157],[18.47441,46.10136],[18.47293,46.10149],[18.47256,46.10129],[18.47246,46.10104],[18.47281,46.10022],[18.47214,46.0982],[18.47208,46.09693],[18.46914,46.09389],[18.46747,46.09325],[18.46587,46.09331],[18.46423,46.09409],[18.46355,46.09509],[18.4623,46.09912],[18.46161,46.10044],[18.4609,46.10084],[18.46038,46.10084],[18.45846,46.10036],[18.45769,46.10047],[18.45636,46.10149],[18.45568,46.10209],[18.45304,46.10499],[18.45043,46.10691],[18.44903,46.1086],[18.44831,46.10897],[18.44624,46.11086],[18.44462,46.11159],[18.43796,46.12081],[18.43818,46.12267],[18.43703,46.12692],[18.43631,46.12805],[18.4364,46.12915],[18.4343,46.13362],[18.43132,46.13702],[18.43082,46.13917],[18.43108,46.13998],[18.4294,46.14088],[18.42922,46.14245],[18.4253,46.14767],[18.4246,46.14962],[18.42384,46.1506],[18.42236,46.156],[18.42242,46.15725],[18.42211,46.15788],[18.42208,46.15822]]]}},{"type":"Feature","id":"f4798","properties":{"name":"Sopianae-Antiana","type":"Secondary Road","certainty":"Conjectured","description":"Continues east to Ad Novas/Ad Militare","citation":"Jens Christoffersen","bibliography":"BAtlas 20, Löhberg 2010","itinerary":"Itinerarium Antonini"},"geometry":{"type":"MultiLineString","coordinates":[[[18.79228,45.83435],[18.78779,45.833],[18.7808,45.83165],[18.77851,45.8319],[18.77732,45.83275],[18.77498,45.83297],[18.77382,45.83293],[18.76984,45.83223],[18.76437,45.83029],[18.7578,45.82583],[18.75725,45.82446],[18.75658,45.82316],[18.75113,45.81887],[18.7406,45.81673],[18.73938,45.81627],[18.73774,45.81601],[18.73344,45.81628],[18.73063,45.81639],[18.72964,45.81623],[18.7273,45.81629],[18.72527,45.81659],[18.72315,45.81789],[18.72052,45.81891],[18.71916,45.81914],[18.7161,45.81932],[18.7039,45.81896],[18.70021,45.81833],[18.69722,45.81719],[18.68288,45.81465],[18.66943,45.81362],[18.66998,45.81255],[18.67031,45.80961],[18.66646,45.80924],[18.66404,45.80846],[18.65905,45.80827],[18.65976,45.80634],[18.65921,45.8062],[18.63769,45.80984],[18.63346,45.80848],[18.60356,45.82795],[18.5949,45.83128],[18.59269,45.83783],[18.59084,45.83963],[18.582,45.85123],[18.56849,45.85504],[18.56478,45.86045],[18.55631,45.86307],[18.54255,45.86362],[18.5308,45.86618],[18.52228,45.86672],[18.5112,45.87208],[18.49957,45.8842],[18.5003,45.88608],[18.49787,45.88639],[18.49805,45.88858],[18.49653,45.9035],[18.49172,45.91059],[18.47802,45.92096],[18.46851,45.93798],[18.46119,45.95187],[18.44289,45.96576],[18.43522,45.97147],[18.42504,45.97708],[18.41106,45.98926],[18.40649,45.99496],[18.39593,45.99991],[18.36064,46.02227],[18.32487,46.04215],[18.30937,46.05099],[18.28349,46.05484],[18.28271,46.05698],[18.28072,46.05994],[18.27585,46.06224],[18.27536,46.06366],[18.27305,46.06676],[18.26775,46.07171],[18.25906,46.07861],[18.25291,46.07901]]]}},{"type":"Feature","id":"f4803","properties":{"name":"Gorsium-southwest","type":"Secondary Road","certainty":"Conjectured","citation":"Jens Christoffersen","bibliography":"BAtlas 20, Löhberg 2010","itinerary":"Itinerarium Antonini"},"geometry":{"type":"MultiLineString","coordinates":[[[18.24294,46.9295],[18.24785,46.93053],[18.25095,46.93084],[18.2468,46.93573],[18.2525,46.94121],[18.25997,46.95391],[18.26831,46.97404],[18.27632,46.9919],[18.28379,47.00413],[18.28816,47.0124],[18.36026,47.05132],[18.40215,47.07915],[18.40569,47.08382],[18.41609,47.08791],[18.41956,47.09129]]]}},{"type":"Feature","id":"f4823","properties":{"name":"Caesariana-southeast","type":"Secondary Road","certainty":"Conjectured","citation":"Jens Christoffersen","bibliography":"BAtlas 20, Löhberg 2010","itinerary":"Itinerarium Antonini"},"geometry":{"type":"MultiLineString","coordinates":[[[18.03885,47.09204],[18.04199,47.09123],[18.0475,47.08993],[18.05131,47.08761],[18.07451,47.06922],[18.09125,47.04991],[18.09137,47.04857],[18.09965,47.04174],[18.1073,47.03783],[18.10865,47.03587],[18.11006,47.03561],[18.11688,47.03392],[18.11991,47.03289],[18.13267,47.03086],[18.13609,47.02807],[18.14182,47.02587],[18.14381,47.02366],[18.14684,47.02313],[18.14952,47.0215],[18.15622,47.01925],[18.16498,47.01714],[18.17115,47.01203],[18.17817,47.00183],[18.18026,46.99782],[18.18773,46.99138]]]}},{"type":"Feature","id":"f4834","properties":{"name":"Balaton southeast connecting road","type":"Secondary Road","certainty":"Conjectured","citation":"Jens Christoffersen","bibliography":"BAtlas 20, Löhberg 2010","itinerary":"Itinerarium Antonini"},"geometry":{"type":"MultiLineString","coordinates":[[[18.24294,46.9295],[18.24116,46.93176],[18.23886,46.93418],[18.23749,46.93632],[18.23624,46.93757],[18.23333,46.93895],[18.23259,46.9397],[18.22817,46.95072],[18.22598,46.95271],[18.22212,46.95355],[18.21905,46.95492],[18.21681,46.95665],[18.21259,46.96223],[18.20549,46.97141],[18.2009,46.97808],[18.19809,46.9807],[18.19676,46.98149],[18.19245,46.98525],[18.19035,46.98854],[18.18773,46.99138]]]}}]}